[{
    "username": "Flora",
    "pwd": "store",
    "time_regis": "1/29/2060"
},
{
    "username": "Luke",
    "pwd": "speech",
    "time_regis": "6/28/2047"
},
{
    "username": "Christina",
    "pwd": "stream",
    "time_regis": "2/24/2121"
},
{
    "username": "Verna",
    "pwd": "addition",
    "time_regis": "1/18/2036"
},
{
    "username": "Nicholas",
    "pwd": "familiar",
    "time_regis": "12/16/2031"
},
{
    "username": "Julia",
    "pwd": "climate",
    "time_regis": "5/16/2109"
},
{
    "username": "Estelle",
    "pwd": "lack",
    "time_regis": "6/12/2109"
}]